pymep/__init__.py
pymep/complex.py
pymep/complexParser.py
pymep/complexParserTest.py
pymep/complexTest.py
pymep/exception.py
pymep/realParser.py
pymep/realParserTest.py
pymep-1.0.7.dist-info/LICENSE
pymep-1.0.7.dist-info/METADATA
pymep-1.0.7.dist-info/WHEEL
pymep-1.0.7.dist-info/top_level.txt
pymep-1.0.7.dist-info/RECORD
