Metadata-Version: 2.1
Name: pymep
Version: 1.0.7
Summary: Python Math Expression Parser
Home-page: https://github.com/sbesada/python.math.expression.parser.pymep
Author: Sergio Besada
Author-email: sergio.besada@gmail.com
License: UNKNOWN
Platform: UNKNOWN
Classifier: Programming Language :: Python :: 3
Classifier: License :: OSI Approved :: Apache Software License
Classifier: Operating System :: OS Independent
